pyplanhat/__init__.py
pyplanhat/_exceptions.py
pyplanhat/py.typed
pyplanhat/_async/__init__.py
pyplanhat/_async/client.py
pyplanhat/_async/resources/__init__.py
pyplanhat/_async/resources/base.py
pyplanhat/_async/resources/companies.py
pyplanhat/_async/resources/conversations.py
pyplanhat/_async/resources/endusers.py
pyplanhat/_sync/__init__.py
pyplanhat/_sync/client.py
pyplanhat/_sync/resources/__init__.py
pyplanhat/_sync/resources/base.py
pyplanhat/_sync/resources/companies.py
pyplanhat/_sync/resources/conversations.py
pyplanhat/_sync/resources/endusers.py
pyplanhat-0.2.1.dist-info/METADATA
pyplanhat-0.2.1.dist-info/WHEEL
pyplanhat-0.2.1.dist-info/entry_points.txt
pyplanhat-0.2.1.dist-info/licenses/LICENSE
pyplanhat-0.2.1.dist-info/RECORD
