Metadata-Version: 2.4
Name: pyplanhat
Version: 0.2.1
Summary: Pythonic wrapper for the Planhat REST API
Project-URL: Homepage, https://github.com/ddlaws0n/pyplanhat
Project-URL: Documentation, https://github.com/ddlaws0n/pyplanhat#readme
Project-URL: Repository, https://github.com/ddlaws0n/pyplanhat.git
Project-URL: Bug Tracker, https://github.com/ddlaws0n/pyplanhat/issues
Author-email: David D Lawson <david@lawson.dev>
License-Expression: MIT
License-File: LICENSE
Keywords: api,crm,planhat,rest,sdk,wrapper
Classifier: Development Status :: 3 - Alpha
Classifier: Intended Audience :: Developers
Classifier: License :: OSI Approved :: MIT License
Classifier: Operating System :: OS Independent
Classifier: Programming Language :: Python :: 3
Classifier: Programming Language :: Python :: 3.10
Classifier: Programming Language :: Python :: 3.11
Classifier: Programming Language :: Python :: 3.12
Classifier: Programming Language :: Python :: 3.13
Classifier: Topic :: Internet :: WWW/HTTP
Classifier: Topic :: Office/Business
Classifier: Topic :: Software Development :: Libraries :: Python Modules
Classifier: Typing :: Typed
Requires-Python: >=3.10
Requires-Dist: httpx>=0.27.0
Requires-Dist: pydantic>=2.0.0
Provides-Extra: dev
Requires-Dist: coverage; extra == 'dev'
Requires-Dist: ipython; extra == 'dev'
Requires-Dist: mypy; extra == 'dev'
Requires-Dist: pytest; extra == 'dev'
Requires-Dist: pytest-asyncio>=0.21.0; extra == 'dev'
Requires-Dist: pytest-cov; extra == 'dev'
Requires-Dist: pytest-httpx>=0.30.0; extra == 'dev'
Requires-Dist: ruff; extra == 'dev'
Requires-Dist: twine; extra == 'dev'
Requires-Dist: unasync>=0.5.0; extra == 'dev'
Provides-Extra: test
Requires-Dist: pytest; extra == 'test'
Requires-Dist: pytest-asyncio>=0.21.0; extra == 'test'
Requires-Dist: pytest-cov; extra == 'test'
Requires-Dist: pytest-httpx>=0.30.0; extra == 'test'
